ez_setup.py
setup.py
nestoria/__init__.py
nestoria/api.py
nestoria/ez_setup.py
nestoria.egg-info/PKG-INFO
nestoria.egg-info/SOURCES.txt
nestoria.egg-info/dependency_links.txt
nestoria.egg-info/entry_points.txt
nestoria.egg-info/requires.txt
nestoria.egg-info/top_level.txt
