Metadata-Version: 1.0
Name: nestoria
Version: 0.31
Summary: Wrapper for www.nestoria.co.uk API
Home-page: http://www.nestoria.co.uk/help/api-tech
Author: CodeSyntax
Author-email: fquintana@codesyntax.com
License: GPL
Platform: any
Classifier: Intended Audience :: Developers
Classifier: Programming Language :: Python
Classifier: Topic :: Internet :: WWW/HTTP
